LICENSE
README.md
pyproject.toml
src/numba_midi/__init__.py
src/numba_midi/_score_numba.py
src/numba_midi/controls.py
src/numba_midi/instruments.py
src/numba_midi/midi.py
src/numba_midi/midi_draw.py
src/numba_midi/numba_draw.py
src/numba_midi/pianoroll.py
src/numba_midi/py.typed
src/numba_midi/score.py
src/numba_midi/utils.py
src/numba_midi.egg-info/PKG-INFO
src/numba_midi.egg-info/SOURCES.txt
src/numba_midi.egg-info/dependency_links.txt
src/numba_midi.egg-info/requires.txt
src/numba_midi.egg-info/top_level.txt
src/numba_midi/interop/pretty_midi.py
src/numba_midi/interop/symusic.py
src/numba_midi/interop/tinysoundfont.py
tests/test_benchmarks.py
tests/test_drawing_regression.py
tests/test_midi.py
tests/test_pianoroll.py
tests/test_score.py