Metadata-Version: 2.4
Name: numba_midi
Version: 0.1.29
Summary: numba-accelerated python midi score processing library.
Author: Martin de La Gorce
License: MIT
Project-URL: Homepage, https://github.com/martinResearch/numba_midi
Requires-Python: >=3.11
License-File: LICENSE
Requires-Dist: numba>=0.61
Requires-Dist: numpy
Provides-Extra: dev
Requires-Dist: ruff; extra == "dev"
Requires-Dist: pytest; extra == "dev"
Requires-Dist: mypy; extra == "dev"
Requires-Dist: types-pyaudio; extra == "dev"
Requires-Dist: symusic; extra == "dev"
Requires-Dist: tqdm; extra == "dev"
Requires-Dist: pretty_midi; extra == "dev"
Requires-Dist: symusic; extra == "dev"
Requires-Dist: tinysoundfont; extra == "dev"
Requires-Dist: setuptools; extra == "dev"
Requires-Dist: requests; extra == "dev"
Requires-Dist: types-requests; extra == "dev"
Requires-Dist: pandas; extra == "dev"
Requires-Dist: Pillow; extra == "dev"
Dynamic: license-file
